opcode_decoder.v
`timescale 1ns / 1ps

/*
 * Opcode Decoder
Ye module Operation code generate karta hai jo Control unit use karta hai Jisse Testbench Execute karta hai . 

 * NOP: 0000, //0
 
   ADD: 0001, //1 ALU
   
   SUB: 0010, //2 ALU
   
   LOAD: 0011, //3  Memory
   
   STORE: 0100 //4 Memory
   
 */
module opcode_decoder (
    input [3:0] Opcode,
    
    output is_ADD, // outputs are defiend e.g ADD,SUB,LOAD,STORE,NOP
    
    output is_SUB,
    
    output is_LOAD,
    
    output is_STORE,
    
    output is_NOP
);

    // Opcodes are used in testbench
        parameter OP_NOP   = 4'b0000;
        
    parameter OP_ADD   = 4'b0001;
    
    parameter OP_SUB   = 4'b0010;
    
        parameter OP_LOAD  = 4'b0011;
        
    parameter OP_STORE = 4'b0100;
// Yahape sahi hai kya ->
    // Combinational logic 
    assign is_ADD   = (Opcode == OP_ADD); // here we set which operation is generated by the opcode this goes into contorol unit
    
    assign is_SUB   = (Opcode == OP_SUB);
    
    assign is_LOAD  = (Opcode == OP_LOAD);
    
    assign is_STORE = (Opcode == OP_STORE);
    
    assign is_NOP   = (Opcode == OP_NOP);
    
endmodule

control_unit.v

// FSM-based Hardwired Control Unit Control unit VF

// Author : G10 Cs203 
module control_unit(
    input clk,
    input rst,
    input [3:0] Opcode,
    output reg reg_write,
    output reg mem_read,
    output reg mem_write,
    output reg pc_inc,
    output reg ir_load,
    output reg mem_to_reg,
    output reg [1:0] alu_op
);

    // FSM State 
     // Each state corresponds to a instruction execution.
    localparam FETCH     = 3'd0,
               DECODE    = 3'd1,
               EXEC_ALU  = 3'd2,
               WB_ALU    = 3'd3,
               EXEC_MEM  = 3'd4,
               WB_MEM    = 3'd5;

    // ALU Operation 
    localparam ALU_ADD  = 2'b00, // These are the numbring of operations 
               ALU_SUB  = 2'b01,
               ALU_PASS = 2'b10;  // For address calculation / default

    
    reg [2:0] state, next_state;
    wire is_ADD, is_SUB, is_LOAD, is_STORE, is_NOP;  // Here are the wires

   
    opcode_decoder decoder_inst(  // Yaha Decoder ko start kiya hai 
        .Opcode(Opcode),  
        .is_ADD(is_ADD), .is_SUB(is_SUB), .is_LOAD(is_LOAD),
        .is_STORE(is_STORE), .is_NOP(is_NOP)
    );

   
    // State Register
  
    always @(posedge clk or posedge rst) begin  // Ye Positive edge Trigerred Hai
        if (rst)
            state <= FETCH;  // State 0
        else
            state <= next_state; //State ++
    end

  
    // Next-State Logic
   // what happen in next state --
    always @(*) begin
        next_state = state;
        case (state)
            FETCH:  next_state = DECODE;
            
            DECODE: begin
                if (is_ADD || is_SUB)
                
                next_state = EXEC_ALU;
                   
                else if (is_LOAD || is_STORE)
                
                   next_state = EXEC_MEM;
                else
              next_state = FETCH; // NOP
            end
               EXEC_ALU: next_state = WB_ALU;
               
          WB_ALU:   next_state = FETCH;
            
         EXEC_MEM: next_state = is_LOAD ? WB_MEM : FETCH;
         
             WB_MEM:   next_state = FETCH;
              
            default:  next_state = FETCH;
        endcase
    end

    //=====================
    // Output Logic (Combinational)
    //=====================
    always @(*) begin
        // Default outputs
        reg_write  = 0;
        mem_read   = 0;
        mem_write  = 0;
        pc_inc     = 0;
        ir_load    = 0;
        mem_to_reg = 0;
        alu_op     = ALU_PASS;

        case (state)
            FETCH: begin
                pc_inc   = 1;
                mem_read = 1;
                ir_load  = 1;
            end
            DECODE: ; // no control signals
            EXEC_ALU: alu_op = is_ADD ? ALU_ADD : (is_SUB ? ALU_SUB : ALU_PASS);
            
            WB_ALU: begin
                reg_write  = 1;
                
                mem_to_reg = 0; // write th ALU result
            end
            EXEC_MEM: begin
                alu_op = ALU_PASS; // address calculations
                if (is_LOAD)
                
                    mem_read = 1;
                else if (is_STORE)
                    mem_write = 1;
                    
            end
            WB_MEM: begin
                reg_write  = 1;
                mem_to_reg = 1; // write the data to the memory back
                
            end
        endcase
    end
endmodule

control_unit_tb.v

`timescale 1ns/1ps

module control_unit_tb;


    // DUT I/O Signals

    reg clk, rst;
    reg [3:0] Opcode;  //Opcode ~ opcode 
    wire reg_write, mem_read, mem_write, pc_inc, ir_load, mem_to_reg;
    
    wire [1:0] alu_op;

    
    // Initializing DUT
   
    control_unit DUT (
        .clk(clk),
        
        .rst(rst),
        
        .Opcode(Opcode),
        
        .reg_write(reg_write),
        
        .mem_read(mem_read),
        
        .mem_write(mem_write),
        
        .pc_inc(pc_inc),
        
        .ir_load(ir_load),
        
        .mem_to_reg(mem_to_reg),
        
        .alu_op(alu_op)
    );

    // ------------------------------
    // Clock period is set to 10 ns consdering the Flip Flop and Gate delays ~5-6 ns
    // ------------------------------
    always #5 clk = ~clk; // This is on for 5 ns the off for 5 ns
    
    // Clock generation
    // 10 ns period = 100 MHz
    // ("#5" = half period toggling)

    // Start Simulatin Here
    initial begin
        $dumpfile("control_unit.vcd"); // for GTKWave
        $dumpvars(0, control_unit_tb);

        clk = 0;
        rst = 1;
        Opcode = 4'b0000;

        #10 rst = 0; // 10ns after reset clk

        $display("\n====================================================");
        $display("                CONTROL UNIT FSM                 ");
        $display("====================================================\n");

        
        // 1. BASIC INSTRUCTION TESTS
        
        $display("--------------- Test 1: BASIC INSTRUCTION SET ---------------");
        Opcode = 4'b0000;  #40;   // NOP
        Opcode = 4'b0001;  #40;   // ADD
        
        Opcode = 4'b0010;  #40;   // SUB
        Opcode = 4'b0011;  #60;   // LOAD
        
        Opcode = 4'b0100;  #60;   // STORE
        $display("-------------------------------------------------------------\n");

       
        // 2. SEQUENTIAL INSTRUCTION MIX
        
        $display("--------------- Test 2: ADD -> STORE -> SUB -> LOAD -> NOP ---------------");
        Opcode = 4'b0001;  #40;  // ADD
        
        Opcode = 4'b0100;  #40;   // STORE
        
        Opcode = 4'b0010;  #40;   // SUB
        
        Opcode = 4'b0011;  #40;  // LOAD
        
        Opcode = 4'b0000;  #40;   // NOP
        $display("--------------------------------------------------------------------------\n");

        // =======================================================
        // 3. UNDEFINED OPCODES
        // =======================================================
        $display("--------------- Test 3: UNDEFINED OPCODES (0101, 1111) ---------------");
        Opcode = 4'b0101;  #40;  // Undefined → acts as NOP
        
        Opcode = 4'b1111;  #40;  // Undefined → acts as NOP
        $display("---------------------------------------------------------------------\n");

        // =======================================================
        // 4. REPEATED MEMORY INSTRUCTIONS
        // =======================================================
        $display("--------------- Test 4: REPEATED LOAD & STORE ---------------");
        Opcode = 4'b0011;  #40;  // LOAD
        
       Opcode = 4'b0011;  #40;   // LOAD again
       
          Opcode = 4'b0100;  #40;  // STORE
          
            Opcode = 4'b0100;  #40;   // STORE again
        $display("-------------------------------------------------------------\n");

       
        // 5. ALTERNATING ALU / MEMORY INSTRUCTIONS
        
        $display("--------------- Test 5: ADD -> LOAD -> SUB -> STORE ---------------");
        Opcode = 4'b0001;  #40;   // ADD
       Opcode = 4'b0011;  #40;   // LOAD
           Opcode = 4'b0010;  #40;   // SUB
        Opcode = 4'b0100;  #40;   // STORE
        $display("---------------------------------------------------------------\n");

       
        // 6. NOP FLOOD STABILITY TEST
       
        $display("--------------- Test 6: NOP FLOOD (STABILITY CHECK) ---------------");
        Opcode = 4'b0000;  #200;  // FSM should loop FETCH <-> DECODE
        $display("------------------------------------------------------------------\n");

        // End of Simulation
       $display("\n====================================================");
        $display("         ALL EXTENDED TESTS COMPLETED SUCCESSFULLY");
          $display("====================================================\n");

        $finish;
    end

    //yahan pe hum har clock pe state print kar rahe hain
    always @(posedge clk) begin
        $display("[%8t ns]  State=%0d | Opcode=%b | pc_inc=%b | mem_read=%b | mem_write=%b | alu_op=%b | reg_write=%b | mem_to_reg=%b | ir_load=%b",
                 $realtime/1000.0, DUT.state, Opcode, pc_inc, mem_read, mem_write, alu_op, reg_write, mem_to_reg, ir_load);
    end

endmodule

control_unit.vcd
$date
	Mon Nov 10 05:14:56 2025
$end
$version
	Icarus Verilog
$end
$timescale
	1ps
$end
$scope module control_unit_tb $end
$var wire 1 ! reg_write $end
$var wire 1 " pc_inc $end
$var wire 1 # mem_write $end
$var wire 1 $ mem_to_reg $end
$var wire 1 % mem_read $end
$var wire 1 & ir_load $end
$var wire 2 ' alu_op [1:0] $end
$var reg 4 ( Opcode [3:0] $end
$var reg 1 ) clk $end
$var reg 1 * rst $end
$scope module DUT $end
$var wire 4 + Opcode [3:0] $end
$var wire 1 ) clk $end
$var wire 1 * rst $end
$var wire 1 , is_SUB $end
$var wire 1 - is_STORE $end
$var wire 1 . is_NOP $end
$var wire 1 / is_LOAD $end
$var wire 1 0 is_ADD $end
$var parameter 2 1 ALU_ADD $end
$var parameter 2 2 ALU_PASS $end
$var parameter 2 3 ALU_SUB $end
$var parameter 3 4 DECODE $end
$var parameter 3 5 EXEC_ALU $end
$var parameter 3 6 EXEC_MEM $end
$var parameter 3 7 FETCH $end
$var parameter 3 8 WB_ALU $end
$var parameter 3 9 WB_MEM $end
$var reg 2 : alu_op [1:0] $end
$var reg 1 & ir_load $end
$var reg 1 % mem_read $end
$var reg 1 $ mem_to_reg $end
$var reg 1 # mem_write $end
$var reg 3 ; next_state [2:0] $end
$var reg 1 " pc_inc $end
$var reg 1 ! reg_write $end
$var reg 3 < state [2:0] $end
$scope module decoder_inst $end
$var wire 4 = Opcode [3:0] $end
$var wire 1 , is_SUB $end
$var wire 1 - is_STORE $end
$var wire 1 . is_NOP $end
$var wire 1 / is_LOAD $end
$var wire 1 0 is_ADD $end
$var parameter 4 > OP_ADD $end
$var parameter 4 ? OP_LOAD $end
$var parameter 4 @ OP_NOP $end
$var parameter 4 A OP_STORE $end
$var parameter 4 B OP_SUB $end
$upscope $end
$upscope $end
$upscope $end
$enddefinitions $end
$comment Show the parameter values. $end
$dumpall
b10 B
b100 A
b0 @
b11 ?
b1 >
b101 9
b11 8
b0 7
b100 6
b10 5
b1 4
b1 3
b10 2
b0 1
$end
#0
$dumpvars
b0 =
b0 <
b1 ;
b10 :
00
0/
1.
0-
0,
b0 +
1*
0)
b0 (
b10 '
1&
1%
0$
0#
1"
0!
$end
#5000
1)
#10000
0)
0*
#15000
0&
0"
0%
b0 ;
b1 <
1)
#20000
0)
#25000
b1 ;
1&
1%
1"
b0 <
1)
#30000
0)
#35000
0&
0"
0%
b0 ;
b1 <
1)
#40000
0)
#45000
b1 ;
1&
1%
1"
b0 <
1)
#50000
1&
1"
1%
b1 ;
0)
10
0.
b1 (
b1 +
b1 =
#55000
b10 ;
0&
0"
0%
b1 <
1)
#60000
0)
#65000
b0 '
b0 :
b11 ;
b10 <
1)
#70000
0)
#75000
b0 ;
1!
b10 '
b10 :
b11 <
1)
#80000
0)
#85000
1&
1%
1"
0!
b1 ;
b0 <
1)
#90000
b1 ;
1&
1"
1%
0)
00
1,
b10 (
b10 +
b10 =
#95000
0&
0"
0%
b10 ;
b1 <
1)
#100000
0)
#105000
b11 ;
b1 '
b1 :
b10 <
1)
#110000
0)
#115000
1!
b10 '
b10 :
b0 ;
b11 <
1)
#120000
0)
#125000
b1 ;
1&
1%
1"
0!
b0 <
1)
#130000
1&
1"
1%
b1 ;
0)
0,
1/
b11 (
b11 +
b11 =
#135000
b100 ;
0&
0"
0%
b1 <
1)
#140000
0)
#145000
1%
b101 ;
b100 <
1)
#150000
0)
#155000
b0 ;
1$
1!
0%
b101 <
1)
#160000
0)
#165000
1&
1%
1"
0$
0!
b1 ;
b0 <
1)
#170000
0)
#175000
b100 ;
0&
0"
0%
b1 <
1)
#180000
0)
#185000
1%
b101 ;
b100 <
1)
#190000
b0 ;
1#
0%
0)
0/
1-
b100 (
b100 +
b100 =
#195000
1&
1%
1"
0#
b1 ;
b0 <
1)
#200000
0)
#205000
b100 ;
0&
0"
0%
b1 <
1)
#210000
0)
#215000
1#
b0 ;
b100 <
1)
#220000
0)
#225000
b1 ;
1&
1%
1"
0#
b0 <
1)
#230000
0)
#235000
0&
0"
0%
b100 ;
b1 <
1)
#240000
0)
#245000
b0 ;
1#
b100 <
1)
#250000
0#
b0 ;
0)
10
0-
b1 (
b1 +
b1 =
#255000
b1 ;
1&
1%
1"
b0 <
1)
#260000
0)
#265000
0&
0"
0%
b10 ;
b1 <
1)
#270000
0)
#275000
b11 ;
b0 '
b0 :
b10 <
1)
#280000
0)
#285000
1!
b10 '
b10 :
b0 ;
b11 <
1)
#290000
b0 ;
1!
0)
00
1-
b100 (
b100 +
b100 =
#295000
1&
1%
1"
0!
b1 ;
b0 <
1)
#300000
0)
#305000
b100 ;
0&
0"
0%
b1 <
1)
#310000
0)
#315000
1#
b0 ;
b100 <
1)
#320000
0)
#325000
b1 ;
1&
1%
1"
0#
b0 <
1)
#330000
1&
1"
1%
b1 ;
0)
1,
0-
b10 (
b10 +
b10 =
#335000
b10 ;
0&
0"
0%
b1 <
1)
#340000
0)
#345000
b1 '
b1 :
b11 ;
b10 <
1)
#350000
0)
#355000
b0 ;
1!
b10 '
b10 :
b11 <
1)
#360000
0)
#365000
1&
1%
1"
0!
b1 ;
b0 <
1)
#370000
b1 ;
1&
1"
1%
0)
0,
1/
b11 (
b11 +
b11 =
#375000
0&
0"
0%
b100 ;
b1 <
1)
#380000
0)
#385000
b101 ;
1%
b100 <
1)
#390000
0)
#395000
1$
1!
0%
b0 ;
b101 <
1)
#400000
0)
#405000
b1 ;
1&
1%
1"
0$
0!
b0 <
1)
#410000
1&
1"
1%
b1 ;
0)
0/
1.
b0 (
b0 +
b0 =
#415000
b0 ;
0&
0"
0%
b1 <
1)
#420000
0)
#425000
1&
1%
1"
b1 ;
b0 <
1)
#430000
0)
#435000
b0 ;
0&
0"
0%
b1 <
1)
#440000
0)
#445000
1&
1%
1"
b1 ;
b0 <
1)
#450000
0)
0.
b101 (
b101 +
b101 =
#455000
b0 ;
0&
0"
0%
b1 <
1)
#460000
0)
#465000
1&
1%
1"
b1 ;
b0 <
1)
#470000
0)
#475000
b0 ;
0&
0"
0%
b1 <
1)
#480000
0)
#485000
1&
1%
1"
b1 ;
b0 <
1)
#490000
0)
b1111 (
b1111 +
b1111 =
#495000
b0 ;
0&
0"
0%
b1 <
1)
#500000
0)
#505000
1&
1%
1"
b1 ;
b0 <
1)
#510000
0)
#515000
b0 ;
0&
0"
0%
b1 <
1)
#520000
0)
#525000
1&
1%
1"
b1 ;
b0 <
1)
#530000
b1 ;
1&
1"
1%
0)
1/
b11 (
b11 +
b11 =
#535000
0&
0"
0%
b100 ;
b1 <
1)
#540000
0)
#545000
b101 ;
1%
b100 <
1)
#550000
0)
#555000
1$
1!
0%
b0 ;
b101 <
1)
#560000
0)
#565000
b1 ;
1&
1%
1"
0$
0!
b0 <
1)
#570000
0)
#575000
0&
0"
0%
b100 ;
b1 <
1)
#580000
0)
#585000
b101 ;
1%
b100 <
1)
#590000
0)
#595000
1$
1!
0%
b0 ;
b101 <
1)
#600000
0)
#605000
b1 ;
1&
1%
1"
0$
0!
b0 <
1)
#610000
1&
1"
1%
b1 ;
0)
0/
1-
b100 (
b100 +
b100 =
#615000
b100 ;
0&
0"
0%
b1 <
1)
#620000
0)
#625000
1#
b0 ;
b100 <
1)
#630000
0)
#635000
b1 ;
1&
1%
1"
0#
b0 <
1)
#640000
0)
#645000
0&
0"
0%
b100 ;
b1 <
1)
#650000
0)
#655000
b0 ;
1#
b100 <
1)
#660000
0)
#665000
1&
1%
1"
0#
b1 ;
b0 <
1)
#670000
0)
#675000
b100 ;
0&
0"
0%
b1 <
1)
#680000
0)
#685000
1#
b0 ;
b100 <
1)
#690000
b0 ;
0#
0)
10
0-
b1 (
b1 +
b1 =
#695000
1&
1%
1"
b1 ;
b0 <
1)
#700000
0)
#705000
b10 ;
0&
0"
0%
b1 <
1)
#710000
0)
#715000
b0 '
b0 :
b11 ;
b10 <
1)
#720000
0)
#725000
b0 ;
1!
b10 '
b10 :
b11 <
1)
#730000
1!
b0 ;
0)
00
1/
b11 (
b11 +
b11 =
#735000
b1 ;
1&
1%
1"
0!
b0 <
1)
#740000
0)
#745000
0&
0"
0%
b100 ;
b1 <
1)
#750000
0)
#755000
b101 ;
1%
b100 <
1)
#760000
0)
#765000
1$
1!
0%
b0 ;
b101 <
1)
#770000
b0 ;
1$
1!
0)
1,
0/
b10 (
b10 +
b10 =
#775000
1&
1%
1"
0$
0!
b1 ;
b0 <
1)
#780000
0)
#785000
b10 ;
0&
0"
0%
b1 <
1)
#790000
0)
#795000
b1 '
b1 :
b11 ;
b10 <
1)
#800000
0)
#805000
b0 ;
1!
b10 '
b10 :
b11 <
1)
#810000
1!
b0 ;
0)
0,
1-
b100 (
b100 +
b100 =
#815000
b1 ;
1&
1%
1"
0!
b0 <
1)
#820000
0)
#825000
0&
0"
0%
b100 ;
b1 <
1)
#830000
0)
#835000
b0 ;
1#
b100 <
1)
#840000
0)
#845000
1&
1%
1"
0#
b1 ;
b0 <
1)
#850000
b1 ;
1&
1"
1%
0)
0-
1.
b0 (
b0 +
b0 =
#855000
0&
0"
0%
b0 ;
b1 <
1)
#860000
0)
#865000
b1 ;
1&
1%
1"
b0 <
1)
#870000
0)
#875000
0&
0"
0%
b0 ;
b1 <
1)
#880000
0)
#885000
b1 ;
1&
1%
1"
b0 <
1)
#890000
0)
#895000
0&
0"
0%
b0 ;
b1 <
1)
#900000
0)
#905000
b1 ;
1&
1%
1"
b0 <
1)
#910000
0)
#915000
0&
0"
0%
b0 ;
b1 <
1)
#920000
0)
#925000
b1 ;
1&
1%
1"
b0 <
1)
#930000
0)
#935000
0&
0"
0%
b0 ;
b1 <
1)
#940000
0)
#945000
b1 ;
1&
1%
1"
b0 <
1)
#950000
0)
#955000
0&
0"
0%
b0 ;
b1 <
1)
#960000
0)
#965000
b1 ;
1&
1%
1"
b0 <
1)
#970000
0)
#975000
0&
0"
0%
b0 ;
b1 <
1)
#980000
0)
#985000
b1 ;
1&
1%
1"
b0 <
1)
#990000
0)
#995000
0&
0"
0%
b0 ;
b1 <
1)
#1000000
0)
#1005000
b1 ;
1&
1%
1"
b0 <
1)
#1010000
0)
#1015000
0&
0"
0%
b0 ;
b1 <
1)
#1020000
0)
#1025000
b1 ;
1&
1%
1"
b0 <
1)
#1030000
0)
#1035000
0&
0"
0%
b0 ;
b1 <
1)
#1040000
0)
#1045000
b1 ;
1&
1%
1"
b0 <
1)
